sso_tools/__init__.py
sso_tools/auth.py
sso_tools/configs.py
sso_tools/mixins.py
sso_tools/schemas.py
sso_tools/verify.py
sso_tools-0.1.28.dist-info/METADATA
sso_tools-0.1.28.dist-info/WHEEL
sso_tools-0.1.28.dist-info/top_level.txt
sso_tools-0.1.28.dist-info/RECORD
