Metadata-Version: 2.1
Name: sso-tools
Version: 0.1.28
Summary: OAuth2 인증을 위한 도구
Home-page: https://github.com/lee-lou2/sso-tools
Author: lee-lou2
Author-email: lee@lou2.kr
Keywords: sso,oauth2
Classifier: Programming Language :: Python :: 3.6
Classifier: Programming Language :: Python :: 3.7
Classifier: Programming Language :: Python :: 3.8
Classifier: Programming Language :: Python :: 3.9
Classifier: Programming Language :: Python :: 3.10
Classifier: Programming Language :: Python :: 3.11
Requires-Python: >=3.6
Requires-Dist: requests >=2.31.0
Requires-Dist: PyJWT >=2.8.0
Requires-Dist: pytz >=2023.2
